rosamplepackage
